<?xml version="1.0" encoding="UTF-8"?>
<list xmlns:xsi="http://www.w3.org/2001/XMLSchema-instance" xsi:noNamespaceSchemaLocation="../../../xsd/items.xsd">
	<!-- Recipes Elergia - By Gandalf -->
	<item id="18001" type="EtcItem" name="Recipe - Elegia Helmet (60%)">
		<set name="icon" val="icon.etc_recipe_black_i00" />
		<set name="default_action" val="RECIPE" />
		<set name="etcitem_type" val="RECIPE" />
		<set name="immediate_effect" val="true" />
		<set name="material" val="LIQUID" />
		<set name="weight" val="30" />
		<set name="price" val="437520" />
		<set name="recipe_id" val="937" />
		<set name="is_stackable" val="true" />
		<set name="handler" val="Recipes" />
	</item>
	<item id="18002" type="EtcItem" name="Recipe - Elegia Breastplate (60%)">
		<set name="icon" val="icon.etc_recipe_black_i00" />
		<set name="default_action" val="RECIPE" />
		<set name="etcitem_type" val="RECIPE" />
		<set name="immediate_effect" val="true" />
		<set name="material" val="LIQUID" />
		<set name="weight" val="30" />
		<set name="price" val="437520" />
		<set name="recipe_id" val="938" />
		<set name="is_stackable" val="true" />
		<set name="handler" val="Recipes" />
	</item>
	<item id="18003" type="EtcItem" name="Recipe - Elegia Gaiter(60%)">
		<set name="icon" val="icon.etc_recipe_black_i00" />
		<set name="default_action" val="RECIPE" />
		<set name="etcitem_type" val="RECIPE" />
		<set name="immediate_effect" val="true" />
		<set name="material" val="LIQUID" />
		<set name="weight" val="30" />
		<set name="price" val="437520" />
		<set name="recipe_id" val="939" />
		<set name="is_stackable" val="true" />
		<set name="handler" val="Recipes" />
	</item>
	<item id="18004" type="EtcItem" name="Recipe - Elegia Gloves (60%)">
		<set name="icon" val="icon.etc_recipe_black_i00" />
		<set name="default_action" val="RECIPE" />
		<set name="etcitem_type" val="RECIPE" />
		<set name="immediate_effect" val="true" />
		<set name="material" val="LIQUID" />
		<set name="weight" val="30" />
		<set name="price" val="437520" />
		<set name="recipe_id" val="940" />
		<set name="is_stackable" val="true" />
		<set name="handler" val="Recipes" />
	</item>
	<item id="18005" type="EtcItem" name="Recipe - Elegia Boots (60%)">
		<set name="icon" val="icon.etc_recipe_black_i00" />
		<set name="default_action" val="RECIPE" />
		<set name="etcitem_type" val="RECIPE" />
		<set name="immediate_effect" val="true" />
		<set name="material" val="LIQUID" />
		<set name="weight" val="30" />
		<set name="price" val="437520" />
		<set name="recipe_id" val="941" />
		<set name="is_stackable" val="true" />
		<set name="handler" val="Recipes" />
	</item>
	<item id="18006" type="EtcItem" name="Recipe - Elegia Leather Helmet (60%)">
		<set name="icon" val="icon.etc_recipe_black_i00" />
		<set name="default_action" val="RECIPE" />
		<set name="etcitem_type" val="RECIPE" />
		<set name="immediate_effect" val="true" />
		<set name="material" val="LIQUID" />
		<set name="weight" val="30" />
		<set name="price" val="437520" />
		<set name="recipe_id" val="942" />
		<set name="is_stackable" val="true" />
		<set name="handler" val="Recipes" />
	</item>
	<item id="18007" type="EtcItem" name="Recipe - Elegia Leather Breastplate (60%)">
		<set name="icon" val="icon.etc_recipe_black_i00" />
		<set name="default_action" val="RECIPE" />
		<set name="etcitem_type" val="RECIPE" />
		<set name="immediate_effect" val="true" />
		<set name="material" val="LIQUID" />
		<set name="weight" val="30" />
		<set name="price" val="437520" />
		<set name="recipe_id" val="943" />
		<set name="is_stackable" val="true" />
		<set name="handler" val="Recipes" />
	</item>
	<item id="18008" type="EtcItem" name="Recipe - Elegia Leather Legging (60%)">
		<set name="icon" val="icon.etc_recipe_black_i00" />
		<set name="default_action" val="RECIPE" />
		<set name="etcitem_type" val="RECIPE" />
		<set name="immediate_effect" val="true" />
		<set name="material" val="LIQUID" />
		<set name="weight" val="30" />
		<set name="price" val="437520" />
		<set name="recipe_id" val="944" />
		<set name="is_stackable" val="true" />
		<set name="handler" val="Recipes" />
	</item>
	<item id="18009" type="EtcItem" name="Recipe - Elegia Leather Gloves (60%)">
		<set name="icon" val="icon.etc_recipe_black_i00" />
		<set name="default_action" val="RECIPE" />
		<set name="etcitem_type" val="RECIPE" />
		<set name="immediate_effect" val="true" />
		<set name="material" val="LIQUID" />
		<set name="weight" val="30" />
		<set name="price" val="437520" />
		<set name="recipe_id" val="945" />
		<set name="is_stackable" val="true" />
		<set name="handler" val="Recipes" />
	</item>
	<item id="18010" type="EtcItem" name="Recipe - Elegia Leather Boots (60%)">
		<set name="icon" val="icon.etc_recipe_black_i00" />
		<set name="default_action" val="RECIPE" />
		<set name="etcitem_type" val="RECIPE" />
		<set name="immediate_effect" val="true" />
		<set name="material" val="LIQUID" />
		<set name="weight" val="30" />
		<set name="price" val="437520" />
		<set name="recipe_id" val="946" />
		<set name="is_stackable" val="true" />
		<set name="handler" val="Recipes" />
	</item>
	<item id="18011" type="EtcItem" name="Recipe - Elegia Circlet (60%)">
		<set name="icon" val="icon.etc_recipe_black_i00" />
		<set name="default_action" val="RECIPE" />
		<set name="etcitem_type" val="RECIPE" />
		<set name="immediate_effect" val="true" />
		<set name="material" val="LIQUID" />
		<set name="weight" val="30" />
		<set name="price" val="437520" />
		<set name="recipe_id" val="947" />
		<set name="is_stackable" val="true" />
		<set name="handler" val="Recipes" />
	</item>
	<item id="18012" type="EtcItem" name="Recipe - Elegia Tunic (60%)">
		<set name="icon" val="icon.etc_recipe_black_i00" />
		<set name="default_action" val="RECIPE" />
		<set name="etcitem_type" val="RECIPE" />
		<set name="immediate_effect" val="true" />
		<set name="material" val="LIQUID" />
		<set name="weight" val="30" />
		<set name="price" val="437520" />
		<set name="recipe_id" val="948" />
		<set name="is_stackable" val="true" />
		<set name="handler" val="Recipes" />
	</item>
	<item id="18013" type="EtcItem" name="Recipe - Elegia Stockings (60%)">
		<set name="icon" val="icon.etc_recipe_black_i00" />
		<set name="default_action" val="RECIPE" />
		<set name="etcitem_type" val="RECIPE" />
		<set name="immediate_effect" val="true" />
		<set name="material" val="LIQUID" />
		<set name="weight" val="30" />
		<set name="price" val="437520" />
		<set name="recipe_id" val="949" />
		<set name="is_stackable" val="true" />
		<set name="handler" val="Recipes" />
	</item>
	<item id="18014" type="EtcItem" name="Recipe - Elegia Gauntlet (60%)">
		<set name="icon" val="icon.etc_recipe_black_i00" />
		<set name="default_action" val="RECIPE" />
		<set name="etcitem_type" val="RECIPE" />
		<set name="immediate_effect" val="true" />
		<set name="material" val="LIQUID" />
		<set name="weight" val="30" />
		<set name="price" val="437520" />
		<set name="recipe_id" val="950" />
		<set name="is_stackable" val="true" />
		<set name="handler" val="Recipes" />
	</item>
	<item id="18015" type="EtcItem" name="Recipe - Elegia Shoes (60%)">
		<set name="icon" val="icon.etc_recipe_black_i00" />
		<set name="default_action" val="RECIPE" />
		<set name="etcitem_type" val="RECIPE" />
		<set name="immediate_effect" val="true" />
		<set name="material" val="LIQUID" />
		<set name="weight" val="30" />
		<set name="price" val="437520" />
		<set name="recipe_id" val="951" />
		<set name="is_stackable" val="true" />
		<set name="handler" val="Recipes" />
	</item>
	<item id="18016" type="EtcItem" name="Recipe - Elegia Sigil (60%)">
		<set name="icon" val="icon.etc_recipe_black_i00" />
		<set name="default_action" val="RECIPE" />
		<set name="etcitem_type" val="RECIPE" />
		<set name="immediate_effect" val="true" />
		<set name="material" val="LIQUID" />
		<set name="weight" val="30" />
		<set name="price" val="437520" />
		<set name="recipe_id" val="952" />
		<set name="is_stackable" val="true" />
		<set name="handler" val="Recipes" />
	</item>
	<item id="18017" type="EtcItem" name="Recipe - Elegia Shield (60%)">
		<set name="icon" val="icon.etc_recipe_black_i00" />
		<set name="default_action" val="RECIPE" />
		<set name="etcitem_type" val="RECIPE" />
		<set name="immediate_effect" val="true" />
		<set name="material" val="LIQUID" />
		<set name="weight" val="30" />
		<set name="price" val="437520" />
		<set name="recipe_id" val="953" />
		<set name="is_stackable" val="true" />
		<set name="handler" val="Recipes" />
	</item>
</list>